{".class":"MypyFile","_fullname":"preql.utility","future_import_flags":[],"is_partial_stub_package":false,"is_stub":false,"names":{".class":"SymbolTable","Any":{".class":"SymbolTableNode","cross_ref":"typing.Any","kind":"Gdef"},"Callable":{".class":"SymbolTableNode","cross_ref":"typing.Callable","kind":"Gdef"},"DEFAULT_NAMESPACE":{".class":"SymbolTableNode","cross_ref":"preql.constants.DEFAULT_NAMESPACE","kind":"Gdef"},"INT_HASH_SIZE":{".class":"SymbolTableNode","kind":"Gdef","node":{".class":"Var","flags":["is_ready","is_inferred","has_explicit_value"],"fullname":"preql.utility.INT_HASH_SIZE","name":"INT_HASH_SIZE","type":"builtins.int"}},"List":{".class":"SymbolTableNode","cross_ref":"typing.List","kind":"Gdef"},"Union":{".class":"SymbolTableNode","cross_ref":"typing.Union","kind":"Gdef"},"__annotations__":{".class":"SymbolTableNode","kind":"Gdef","node":{".class":"Var","flags":["is_ready"],"fullname":"preql.utility.__annotations__","name":"__annotations__","type":{".class":"Instance","args":["builtins.str",{".class":"AnyType","missing_import_name":null,"source_any":null,"type_of_any":6}],"type_ref":"builtins.dict"}}},"__doc__":{".class":"SymbolTableNode","kind":"Gdef","node":{".class":"Var","flags":["is_ready"],"fullname":"preql.utility.__doc__","name":"__doc__","type":"builtins.str"}},"__file__":{".class":"SymbolTableNode","kind":"Gdef","node":{".class":"Var","flags":["is_ready"],"fullname":"preql.utility.__file__","name":"__file__","type":"builtins.str"}},"__name__":{".class":"SymbolTableNode","kind":"Gdef","node":{".class":"Var","flags":["is_ready"],"fullname":"preql.utility.__name__","name":"__name__","type":"builtins.str"}},"__package__":{".class":"SymbolTableNode","kind":"Gdef","node":{".class":"Var","flags":["is_ready"],"fullname":"preql.utility.__package__","name":"__package__","type":"builtins.str"}},"hashlib":{".class":"SymbolTableNode","cross_ref":"hashlib","kind":"Gdef"},"string_to_hash":{".class":"SymbolTableNode","kind":"Gdef","node":{".class":"FuncDef","abstract_status":0,"arg_kinds":[0],"arg_names":["input"],"dataclass_transform_spec":null,"flags":[],"fullname":"preql.utility.string_to_hash","name":"string_to_hash","type":{".class":"CallableType","arg_kinds":[0],"arg_names":["input"],"arg_types":["builtins.str"],"bound_args":[],"def_extras":{"first_arg":null},"fallback":"builtins.function","from_concatenate":false,"implicit":false,"imprecise_arg_kinds":false,"is_ellipsis_args":false,"name":"string_to_hash","ret_type":"builtins.int","type_guard":null,"type_is":null,"unpack_kwargs":false,"variables":[]}}},"unique":{".class":"SymbolTableNode","kind":"Gdef","node":{".class":"FuncDef","abstract_status":0,"arg_kinds":[0,0],"arg_names":["inputs","property"],"dataclass_transform_spec":null,"flags":[],"fullname":"preql.utility.unique","name":"unique","type":{".class":"CallableType","arg_kinds":[0,0],"arg_names":["inputs","property"],"arg_types":[{".class":"Instance","args":[{".class":"AnyType","missing_import_name":null,"source_any":null,"type_of_any":4}],"type_ref":"builtins.list"},{".class":"UnionType","items":["builtins.str",{".class":"CallableType","arg_kinds":[2,4],"arg_names":[null,null],"arg_types":[{".class":"AnyType","missing_import_name":null,"source_any":null,"type_of_any":4},{".class":"AnyType","missing_import_name":null,"source_any":null,"type_of_any":4}],"bound_args":[],"def_extras":{},"fallback":"builtins.function","from_concatenate":false,"implicit":false,"imprecise_arg_kinds":false,"is_ellipsis_args":true,"name":null,"ret_type":{".class":"AnyType","missing_import_name":null,"source_any":null,"type_of_any":4},"type_guard":null,"type_is":null,"unpack_kwargs":false,"variables":[]}]}],"bound_args":[],"def_extras":{"first_arg":null},"fallback":"builtins.function","from_concatenate":false,"implicit":false,"imprecise_arg_kinds":false,"is_ellipsis_args":false,"name":"unique","ret_type":{".class":"Instance","args":[{".class":"AnyType","missing_import_name":null,"source_any":null,"type_of_any":2}],"type_ref":"builtins.list"},"type_guard":null,"type_is":null,"unpack_kwargs":false,"variables":[]}}}},"path":"c:\\Users\\ethan\\coding_projects\\pypreql-etl\\.venv\\Lib\\site-packages\\preql\\utility.py"}