{".class":"MypyFile","_fullname":"mashumaro.core.meta.types.pack","future_import_flags":[],"is_partial_stub_package":false,"is_stub":false,"names":{".class":"SymbolTable","Any":{".class":"SymbolTableNode","cross_ref":"typing.Any","kind":"Gdef","module_public":false},"Callable":{".class":"SymbolTableNode","cross_ref":"typing.Callable","kind":"Gdef","module_public":false},"CodeLines":{".class":"SymbolTableNode","cross_ref":"mashumaro.core.meta.code.lines.CodeLines","kind":"Gdef","module_public":false},"Decimal":{".class":"SymbolTableNode","cross_ref":"_decimal.Decimal","kind":"Gdef","module_public":false},"Expression":{".class":"SymbolTableNode","cross_ref":"mashumaro.core.meta.types.common.Expression","kind":"Gdef","module_public":false},"ExpressionWrapper":{".class":"SymbolTableNode","cross_ref":"mashumaro.core.meta.types.common.ExpressionWrapper","kind":"Gdef","module_public":false},"ForwardRef":{".class":"SymbolTableNode","cross_ref":"typing.ForwardRef","kind":"Gdef","module_public":false},"Fraction":{".class":"SymbolTableNode","cross_ref":"fractions.Fraction","kind":"Gdef","module_public":false},"GenericSerializableType":{".class":"SymbolTableNode","cross_ref":"mashumaro.types.GenericSerializableType","kind":"Gdef","module_public":false},"List":{".class":"SymbolTableNode","cross_ref":"typing.List","kind":"Gdef","module_public":false},"NoneType":{".class":"SymbolTableNode","cross_ref":"mashumaro.core.meta.types.common.NoneType","kind":"Gdef","module_public":false},"Optional":{".class":"SymbolTableNode","cross_ref":"typing.Optional","kind":"Gdef","module_public":false},"PY_311_MIN":{".class":"SymbolTableNode","cross_ref":"mashumaro.core.const.PY_311_MIN","kind":"Gdef","module_public":false},"PY_39_MIN":{".class":"SymbolTableNode","cross_ref":"mashumaro.core.const.PY_39_MIN","kind":"Gdef","module_public":false},"PackerRegistry":{".class":"SymbolTableNode","kind":"Gdef","node":{".class":"Var","flags":["is_inferred","has_explicit_value"],"fullname":"mashumaro.core.meta.types.pack.PackerRegistry","name":"PackerRegistry","type":"mashumaro.core.meta.types.common.Registry"}},"Registry":{".class":"SymbolTableNode","cross_ref":"mashumaro.core.meta.types.common.Registry","kind":"Gdef","module_public":false},"SerializableType":{".class":"SymbolTableNode","cross_ref":"mashumaro.types.SerializableType","kind":"Gdef","module_public":false},"SerializationStrategy":{".class":"SymbolTableNode","cross_ref":"mashumaro.types.SerializationStrategy","kind":"Gdef","module_public":false},"Tuple":{".class":"SymbolTableNode","cross_ref":"typing.Tuple","kind":"Gdef","module_public":false},"Type":{".class":"SymbolTableNode","cross_ref":"typing.Type","kind":"Gdef","module_public":false},"Union":{".class":"SymbolTableNode","cross_ref":"typing.Union","kind":"Gdef","module_public":false},"UnserializableDataError":{".class":"SymbolTableNode","cross_ref":"mashumaro.exceptions.UnserializableDataError","kind":"Gdef","module_public":false},"UnserializableField":{".class":"SymbolTableNode","cross_ref":"mashumaro.exceptions.UnserializableField","kind":"Gdef","module_public":false},"UnsupportedSerializationEngine":{".class":"SymbolTableNode","cross_ref":"mashumaro.exceptions.UnsupportedSerializationEngine","kind":"Gdef","module_public":false},"ValueSpec":{".class":"SymbolTableNode","cross_ref":"mashumaro.core.meta.types.common.ValueSpec","kind":"Gdef","module_public":false},"__all__":{".class":"SymbolTableNode","kind":"Gdef","module_public":false,"node":{".class":"Var","flags":["is_inferred","has_explicit_value"],"fullname":"mashumaro.core.meta.types.pack.__all__","name":"__all__","type":{".class":"Instance","args":["builtins.str"],"type_ref":"builtins.list"}}},"__annotations__":{".class":"SymbolTableNode","kind":"Gdef","module_public":false,"node":{".class":"Var","flags":["is_ready"],"fullname":"mashumaro.core.meta.types.pack.__annotations__","name":"__annotations__","type":{".class":"Instance","args":["builtins.str",{".class":"AnyType","missing_import_name":null,"source_any":null,"type_of_any":6}],"type_ref":"builtins.dict"}}},"__doc__":{".class":"SymbolTableNode","kind":"Gdef","module_public":false,"node":{".class":"Var","flags":["is_ready"],"fullname":"mashumaro.core.meta.types.pack.__doc__","name":"__doc__","type":"builtins.str"}},"__file__":{".class":"SymbolTableNode","kind":"Gdef","module_public":false,"node":{".class":"Var","flags":["is_ready"],"fullname":"mashumaro.core.meta.types.pack.__file__","name":"__file__","type":"builtins.str"}},"__name__":{".class":"SymbolTableNode","kind":"Gdef","module_public":false,"node":{".class":"Var","flags":["is_ready"],"fullname":"mashumaro.core.meta.types.pack.__name__","name":"__name__","type":"builtins.str"}},"__package__":{".class":"SymbolTableNode","kind":"Gdef","module_public":false,"node":{".class":"Var","flags":["is_ready"],"fullname":"mashumaro.core.meta.types.pack.__package__","name":"__package__","type":"builtins.str"}},"_pack_annotated_serializable_type":{".class":"SymbolTableNode","kind":"Gdef","module_public":false,"node":{".class":"FuncDef","abstract_status":0,"arg_kinds":[0],"arg_names":["spec"],"dataclass_transform_spec":null,"flags":[],"fullname":"mashumaro.core.meta.types.pack._pack_annotated_serializable_type","name":"_pack_annotated_serializable_type","type":{".class":"CallableType","arg_kinds":[0],"arg_names":["spec"],"arg_types":["mashumaro.core.meta.types.common.ValueSpec"],"bound_args":[],"def_extras":{"first_arg":null},"fallback":"builtins.function","from_concatenate":false,"implicit":false,"imprecise_arg_kinds":false,"is_ellipsis_args":false,"name":"_pack_annotated_serializable_type","ret_type":{".class":"UnionType","items":["builtins.str",{".class":"NoneType"}]},"type_guard":null,"type_is":null,"unpack_kwargs":false,"variables":[]}}},"_pack_with_annotated_serialization_strategy":{".class":"SymbolTableNode","kind":"Gdef","module_public":false,"node":{".class":"FuncDef","abstract_status":0,"arg_kinds":[0,0],"arg_names":["spec","strategy"],"dataclass_transform_spec":null,"flags":[],"fullname":"mashumaro.core.meta.types.pack._pack_with_annotated_serialization_strategy","name":"_pack_with_annotated_serialization_strategy","type":{".class":"CallableType","arg_kinds":[0,0],"arg_names":["spec","strategy"],"arg_types":["mashumaro.core.meta.types.common.ValueSpec","mashumaro.types.SerializationStrategy"],"bound_args":[],"def_extras":{"first_arg":null},"fallback":"builtins.function","from_concatenate":false,"implicit":false,"imprecise_arg_kinds":false,"is_ellipsis_args":false,"name":"_pack_with_annotated_serialization_strategy","ret_type":"builtins.str","type_guard":null,"type_is":null,"unpack_kwargs":false,"variables":[]}}},"clean_id":{".class":"SymbolTableNode","cross_ref":"mashumaro.core.meta.types.common.clean_id","kind":"Gdef","module_public":false},"datetime":{".class":"SymbolTableNode","cross_ref":"datetime","kind":"Gdef","module_public":false},"encodebytes":{".class":"SymbolTableNode","cross_ref":"base64.encodebytes","kind":"Gdef","module_public":false},"ensure_generic_collection":{".class":"SymbolTableNode","cross_ref":"mashumaro.core.meta.types.common.ensure_generic_collection","kind":"Gdef","module_public":false},"ensure_generic_collection_subclass":{".class":"SymbolTableNode","cross_ref":"mashumaro.core.meta.types.common.ensure_generic_collection_subclass","kind":"Gdef","module_public":false},"ensure_generic_mapping":{".class":"SymbolTableNode","cross_ref":"mashumaro.core.meta.types.common.ensure_generic_mapping","kind":"Gdef","module_public":false},"enum":{".class":"SymbolTableNode","cross_ref":"enum","kind":"Gdef","module_public":false},"expr_or_maybe_none":{".class":"SymbolTableNode","cross_ref":"mashumaro.core.meta.types.common.expr_or_maybe_none","kind":"Gdef","module_public":false},"get_args":{".class":"SymbolTableNode","cross_ref":"mashumaro.core.meta.helpers.get_args","kind":"Gdef","module_public":false},"get_class_that_defines_method":{".class":"SymbolTableNode","cross_ref":"mashumaro.core.meta.helpers.get_class_that_defines_method","kind":"Gdef","module_public":false},"get_function_return_annotation":{".class":"SymbolTableNode","cross_ref":"mashumaro.core.meta.helpers.get_function_return_annotation","kind":"Gdef","module_public":false},"get_literal_values":{".class":"SymbolTableNode","cross_ref":"mashumaro.core.meta.helpers.get_literal_values","kind":"Gdef","module_public":false},"get_overridden_serialization_method":{".class":"SymbolTableNode","kind":"Gdef","module_public":false,"node":{".class":"FuncDef","abstract_status":0,"arg_kinds":[0],"arg_names":["spec"],"dataclass_transform_spec":null,"flags":[],"fullname":"mashumaro.core.meta.types.pack.get_overridden_serialization_method","name":"get_overridden_serialization_method","type":{".class":"CallableType","arg_kinds":[0],"arg_names":["spec"],"arg_types":["mashumaro.core.meta.types.common.ValueSpec"],"bound_args":[],"def_extras":{"first_arg":null},"fallback":"builtins.function","from_concatenate":false,"implicit":false,"imprecise_arg_kinds":false,"is_ellipsis_args":false,"name":"get_overridden_serialization_method","ret_type":{".class":"UnionType","items":[{".class":"CallableType","arg_kinds":[2,4],"arg_names":[null,null],"arg_types":[{".class":"AnyType","missing_import_name":null,"source_any":null,"type_of_any":4},{".class":"AnyType","missing_import_name":null,"source_any":null,"type_of_any":4}],"bound_args":[],"def_extras":{},"fallback":"builtins.function","from_concatenate":false,"implicit":false,"imprecise_arg_kinds":false,"is_ellipsis_args":true,"name":null,"ret_type":{".class":"AnyType","missing_import_name":null,"source_any":null,"type_of_any":4},"type_guard":null,"type_is":null,"unpack_kwargs":false,"variables":[]},"builtins.str","mashumaro.core.meta.types.common.ExpressionWrapper",{".class":"NoneType"}]},"type_guard":null,"type_is":null,"unpack_kwargs":false,"variables":[]}}},"ipaddress":{".class":"SymbolTableNode","cross_ref":"ipaddress","kind":"Gdef","module_public":false},"is_dataclass":{".class":"SymbolTableNode","cross_ref":"dataclasses.is_dataclass","kind":"Gdef","module_public":false},"is_final":{".class":"SymbolTableNode","cross_ref":"mashumaro.core.meta.helpers.is_final","kind":"Gdef","module_public":false},"is_generic":{".class":"SymbolTableNode","cross_ref":"mashumaro.core.meta.helpers.is_generic","kind":"Gdef","module_public":false},"is_literal":{".class":"SymbolTableNode","cross_ref":"mashumaro.core.meta.helpers.is_literal","kind":"Gdef","module_public":false},"is_named_tuple":{".class":"SymbolTableNode","cross_ref":"mashumaro.core.meta.helpers.is_named_tuple","kind":"Gdef","module_public":false},"is_new_type":{".class":"SymbolTableNode","cross_ref":"mashumaro.core.meta.helpers.is_new_type","kind":"Gdef","module_public":false},"is_not_required":{".class":"SymbolTableNode","cross_ref":"mashumaro.core.meta.helpers.is_not_required","kind":"Gdef","module_public":false},"is_optional":{".class":"SymbolTableNode","cross_ref":"mashumaro.core.meta.helpers.is_optional","kind":"Gdef","module_public":false},"is_required":{".class":"SymbolTableNode","cross_ref":"mashumaro.core.meta.helpers.is_required","kind":"Gdef","module_public":false},"is_self":{".class":"SymbolTableNode","cross_ref":"mashumaro.core.meta.helpers.is_self","kind":"Gdef","module_public":false},"is_special_typing_primitive":{".class":"SymbolTableNode","cross_ref":"mashumaro.core.meta.helpers.is_special_typing_primitive","kind":"Gdef","module_public":false},"is_type_var":{".class":"SymbolTableNode","cross_ref":"mashumaro.core.meta.helpers.is_type_var","kind":"Gdef","module_public":false},"is_type_var_any":{".class":"SymbolTableNode","cross_ref":"mashumaro.core.meta.helpers.is_type_var_any","kind":"Gdef","module_public":false},"is_type_var_tuple":{".class":"SymbolTableNode","cross_ref":"mashumaro.core.meta.helpers.is_type_var_tuple","kind":"Gdef","module_public":false},"is_typed_dict":{".class":"SymbolTableNode","cross_ref":"mashumaro.core.meta.helpers.is_typed_dict","kind":"Gdef","module_public":false},"is_union":{".class":"SymbolTableNode","cross_ref":"mashumaro.core.meta.helpers.is_union","kind":"Gdef","module_public":false},"is_unpack":{".class":"SymbolTableNode","cross_ref":"mashumaro.core.meta.helpers.is_unpack","kind":"Gdef","module_public":false},"not_none_type_arg":{".class":"SymbolTableNode","cross_ref":"mashumaro.core.meta.helpers.not_none_type_arg","kind":"Gdef","module_public":false},"os":{".class":"SymbolTableNode","cross_ref":"os","kind":"Gdef","module_public":false},"pack_any":{".class":"SymbolTableNode","kind":"Gdef","module_public":false,"node":{".class":"Decorator","func":{".class":"FuncDef","abstract_status":0,"arg_kinds":[0],"arg_names":["spec"],"dataclass_transform_spec":null,"flags":["is_decorated"],"fullname":"mashumaro.core.meta.types.pack.pack_any","name":"pack_any","type":{".class":"CallableType","arg_kinds":[0],"arg_names":["spec"],"arg_types":["mashumaro.core.meta.types.common.ValueSpec"],"bound_args":[],"def_extras":{"first_arg":null},"fallback":"builtins.function","from_concatenate":false,"implicit":false,"imprecise_arg_kinds":false,"is_ellipsis_args":false,"name":"pack_any","ret_type":{".class":"UnionType","items":["builtins.str",{".class":"NoneType"}]},"type_guard":null,"type_is":null,"unpack_kwargs":false,"variables":[]}},"is_overload":false,"var":{".class":"Var","flags":["is_ready","is_inferred"],"fullname":"mashumaro.core.meta.types.pack.pack_any","name":"pack_any","type":{".class":"CallableType","arg_kinds":[0],"arg_names":[null],"arg_types":["mashumaro.core.meta.types.common.ValueSpec"],"bound_args":[],"def_extras":{},"fallback":"builtins.function","from_concatenate":false,"implicit":false,"imprecise_arg_kinds":false,"is_ellipsis_args":false,"name":"pack_any","ret_type":{".class":"UnionType","items":["builtins.str",{".class":"NoneType"}]},"type_guard":null,"type_is":null,"unpack_kwargs":false,"variables":[]}}}},"pack_bool_and_none":{".class":"SymbolTableNode","kind":"Gdef","module_public":false,"node":{".class":"Decorator","func":{".class":"FuncDef","abstract_status":0,"arg_kinds":[0],"arg_names":["spec"],"dataclass_transform_spec":null,"flags":["is_decorated"],"fullname":"mashumaro.core.meta.types.pack.pack_bool_and_none","name":"pack_bool_and_none","type":{".class":"CallableType","arg_kinds":[0],"arg_names":["spec"],"arg_types":["mashumaro.core.meta.types.common.ValueSpec"],"bound_args":[],"def_extras":{"first_arg":null},"fallback":"builtins.function","from_concatenate":false,"implicit":false,"imprecise_arg_kinds":false,"is_ellipsis_args":false,"name":"pack_bool_and_none","ret_type":{".class":"UnionType","items":["builtins.str",{".class":"NoneType"}]},"type_guard":null,"type_is":null,"unpack_kwargs":false,"variables":[]}},"is_overload":false,"var":{".class":"Var","flags":["is_ready","is_inferred"],"fullname":"mashumaro.core.meta.types.pack.pack_bool_and_none","name":"pack_bool_and_none","type":{".class":"CallableType","arg_kinds":[0],"arg_names":[null],"arg_types":["mashumaro.core.meta.types.common.ValueSpec"],"bound_args":[],"def_extras":{},"fallback":"builtins.function","from_concatenate":false,"implicit":false,"imprecise_arg_kinds":false,"is_ellipsis_args":false,"name":"pack_bool_and_none","ret_type":{".class":"UnionType","items":["builtins.str",{".class":"NoneType"}]},"type_guard":null,"type_is":null,"unpack_kwargs":false,"variables":[]}}}},"pack_collection":{".class":"SymbolTableNode","kind":"Gdef","module_public":false,"node":{".class":"Decorator","func":{".class":"FuncDef","abstract_status":0,"arg_kinds":[0],"arg_names":["spec"],"dataclass_transform_spec":null,"flags":["is_decorated"],"fullname":"mashumaro.core.meta.types.pack.pack_collection","name":"pack_collection","type":{".class":"CallableType","arg_kinds":[0],"arg_names":["spec"],"arg_types":["mashumaro.core.meta.types.common.ValueSpec"],"bound_args":[],"def_extras":{"first_arg":null},"fallback":"builtins.function","from_concatenate":false,"implicit":false,"imprecise_arg_kinds":false,"is_ellipsis_args":false,"name":"pack_collection","ret_type":{".class":"UnionType","items":["builtins.str",{".class":"NoneType"}]},"type_guard":null,"type_is":null,"unpack_kwargs":false,"variables":[]}},"is_overload":false,"var":{".class":"Var","flags":["is_ready","is_inferred"],"fullname":"mashumaro.core.meta.types.pack.pack_collection","name":"pack_collection","type":{".class":"CallableType","arg_kinds":[0],"arg_names":[null],"arg_types":["mashumaro.core.meta.types.common.ValueSpec"],"bound_args":[],"def_extras":{},"fallback":"builtins.function","from_concatenate":false,"implicit":false,"imprecise_arg_kinds":false,"is_ellipsis_args":false,"name":"pack_collection","ret_type":{".class":"UnionType","items":["builtins.str",{".class":"NoneType"}]},"type_guard":null,"type_is":null,"unpack_kwargs":false,"variables":[]}}}},"pack_dataclass":{".class":"SymbolTableNode","kind":"Gdef","module_public":false,"node":{".class":"Decorator","func":{".class":"FuncDef","abstract_status":0,"arg_kinds":[0],"arg_names":["spec"],"dataclass_transform_spec":null,"flags":["is_decorated"],"fullname":"mashumaro.core.meta.types.pack.pack_dataclass","name":"pack_dataclass","type":{".class":"CallableType","arg_kinds":[0],"arg_names":["spec"],"arg_types":["mashumaro.core.meta.types.common.ValueSpec"],"bound_args":[],"def_extras":{"first_arg":null},"fallback":"builtins.function","from_concatenate":false,"implicit":false,"imprecise_arg_kinds":false,"is_ellipsis_args":false,"name":"pack_dataclass","ret_type":{".class":"UnionType","items":["builtins.str",{".class":"NoneType"}]},"type_guard":null,"type_is":null,"unpack_kwargs":false,"variables":[]}},"is_overload":false,"var":{".class":"Var","flags":["is_ready","is_inferred"],"fullname":"mashumaro.core.meta.types.pack.pack_dataclass","name":"pack_dataclass","type":{".class":"CallableType","arg_kinds":[0],"arg_names":[null],"arg_types":["mashumaro.core.meta.types.common.ValueSpec"],"bound_args":[],"def_extras":{},"fallback":"builtins.function","from_concatenate":false,"implicit":false,"imprecise_arg_kinds":false,"is_ellipsis_args":false,"name":"pack_dataclass","ret_type":{".class":"UnionType","items":["builtins.str",{".class":"NoneType"}]},"type_guard":null,"type_is":null,"unpack_kwargs":false,"variables":[]}}}},"pack_date_objects":{".class":"SymbolTableNode","kind":"Gdef","module_public":false,"node":{".class":"Decorator","func":{".class":"FuncDef","abstract_status":0,"arg_kinds":[0],"arg_names":["spec"],"dataclass_transform_spec":null,"flags":["is_decorated"],"fullname":"mashumaro.core.meta.types.pack.pack_date_objects","name":"pack_date_objects","type":{".class":"CallableType","arg_kinds":[0],"arg_names":["spec"],"arg_types":["mashumaro.core.meta.types.common.ValueSpec"],"bound_args":[],"def_extras":{"first_arg":null},"fallback":"builtins.function","from_concatenate":false,"implicit":false,"imprecise_arg_kinds":false,"is_ellipsis_args":false,"name":"pack_date_objects","ret_type":{".class":"UnionType","items":["builtins.str",{".class":"NoneType"}]},"type_guard":null,"type_is":null,"unpack_kwargs":false,"variables":[]}},"is_overload":false,"var":{".class":"Var","flags":["is_ready","is_inferred"],"fullname":"mashumaro.core.meta.types.pack.pack_date_objects","name":"pack_date_objects","type":{".class":"CallableType","arg_kinds":[0],"arg_names":[null],"arg_types":["mashumaro.core.meta.types.common.ValueSpec"],"bound_args":[],"def_extras":{},"fallback":"builtins.function","from_concatenate":false,"implicit":false,"imprecise_arg_kinds":false,"is_ellipsis_args":false,"name":"pack_date_objects","ret_type":{".class":"UnionType","items":["builtins.str",{".class":"NoneType"}]},"type_guard":null,"type_is":null,"unpack_kwargs":false,"variables":[]}}}},"pack_decimal":{".class":"SymbolTableNode","kind":"Gdef","module_public":false,"node":{".class":"Decorator","func":{".class":"FuncDef","abstract_status":0,"arg_kinds":[0],"arg_names":["spec"],"dataclass_transform_spec":null,"flags":["is_decorated"],"fullname":"mashumaro.core.meta.types.pack.pack_decimal","name":"pack_decimal","type":{".class":"CallableType","arg_kinds":[0],"arg_names":["spec"],"arg_types":["mashumaro.core.meta.types.common.ValueSpec"],"bound_args":[],"def_extras":{"first_arg":null},"fallback":"builtins.function","from_concatenate":false,"implicit":false,"imprecise_arg_kinds":false,"is_ellipsis_args":false,"name":"pack_decimal","ret_type":{".class":"UnionType","items":["builtins.str",{".class":"NoneType"}]},"type_guard":null,"type_is":null,"unpack_kwargs":false,"variables":[]}},"is_overload":false,"var":{".class":"Var","flags":["is_ready","is_inferred"],"fullname":"mashumaro.core.meta.types.pack.pack_decimal","name":"pack_decimal","type":{".class":"CallableType","arg_kinds":[0],"arg_names":[null],"arg_types":["mashumaro.core.meta.types.common.ValueSpec"],"bound_args":[],"def_extras":{},"fallback":"builtins.function","from_concatenate":false,"implicit":false,"imprecise_arg_kinds":false,"is_ellipsis_args":false,"name":"pack_decimal","ret_type":{".class":"UnionType","items":["builtins.str",{".class":"NoneType"}]},"type_guard":null,"type_is":null,"unpack_kwargs":false,"variables":[]}}}},"pack_enum":{".class":"SymbolTableNode","kind":"Gdef","module_public":false,"node":{".class":"Decorator","func":{".class":"FuncDef","abstract_status":0,"arg_kinds":[0],"arg_names":["spec"],"dataclass_transform_spec":null,"flags":["is_decorated"],"fullname":"mashumaro.core.meta.types.pack.pack_enum","name":"pack_enum","type":{".class":"CallableType","arg_kinds":[0],"arg_names":["spec"],"arg_types":["mashumaro.core.meta.types.common.ValueSpec"],"bound_args":[],"def_extras":{"first_arg":null},"fallback":"builtins.function","from_concatenate":false,"implicit":false,"imprecise_arg_kinds":false,"is_ellipsis_args":false,"name":"pack_enum","ret_type":{".class":"UnionType","items":["builtins.str",{".class":"NoneType"}]},"type_guard":null,"type_is":null,"unpack_kwargs":false,"variables":[]}},"is_overload":false,"var":{".class":"Var","flags":["is_ready","is_inferred"],"fullname":"mashumaro.core.meta.types.pack.pack_enum","name":"pack_enum","type":{".class":"CallableType","arg_kinds":[0],"arg_names":[null],"arg_types":["mashumaro.core.meta.types.common.ValueSpec"],"bound_args":[],"def_extras":{},"fallback":"builtins.function","from_concatenate":false,"implicit":false,"imprecise_arg_kinds":false,"is_ellipsis_args":false,"name":"pack_enum","ret_type":{".class":"UnionType","items":["builtins.str",{".class":"NoneType"}]},"type_guard":null,"type_is":null,"unpack_kwargs":false,"variables":[]}}}},"pack_final":{".class":"SymbolTableNode","kind":"Gdef","module_public":false,"node":{".class":"Decorator","func":{".class":"FuncDef","abstract_status":0,"arg_kinds":[0],"arg_names":["spec"],"dataclass_transform_spec":null,"flags":["is_decorated"],"fullname":"mashumaro.core.meta.types.pack.pack_final","name":"pack_final","type":{".class":"CallableType","arg_kinds":[0],"arg_names":["spec"],"arg_types":["mashumaro.core.meta.types.common.ValueSpec"],"bound_args":[],"def_extras":{"first_arg":null},"fallback":"builtins.function","from_concatenate":false,"implicit":false,"imprecise_arg_kinds":false,"is_ellipsis_args":false,"name":"pack_final","ret_type":{".class":"UnionType","items":["builtins.str",{".class":"NoneType"}]},"type_guard":null,"type_is":null,"unpack_kwargs":false,"variables":[]}},"is_overload":false,"var":{".class":"Var","flags":["is_ready","is_inferred"],"fullname":"mashumaro.core.meta.types.pack.pack_final","name":"pack_final","type":{".class":"CallableType","arg_kinds":[0],"arg_names":[null],"arg_types":["mashumaro.core.meta.types.common.ValueSpec"],"bound_args":[],"def_extras":{},"fallback":"builtins.function","from_concatenate":false,"implicit":false,"imprecise_arg_kinds":false,"is_ellipsis_args":false,"name":"pack_final","ret_type":{".class":"UnionType","items":["builtins.str",{".class":"NoneType"}]},"type_guard":null,"type_is":null,"unpack_kwargs":false,"variables":[]}}}},"pack_fraction":{".class":"SymbolTableNode","kind":"Gdef","module_public":false,"node":{".class":"Decorator","func":{".class":"FuncDef","abstract_status":0,"arg_kinds":[0],"arg_names":["spec"],"dataclass_transform_spec":null,"flags":["is_decorated"],"fullname":"mashumaro.core.meta.types.pack.pack_fraction","name":"pack_fraction","type":{".class":"CallableType","arg_kinds":[0],"arg_names":["spec"],"arg_types":["mashumaro.core.meta.types.common.ValueSpec"],"bound_args":[],"def_extras":{"first_arg":null},"fallback":"builtins.function","from_concatenate":false,"implicit":false,"imprecise_arg_kinds":false,"is_ellipsis_args":false,"name":"pack_fraction","ret_type":{".class":"UnionType","items":["builtins.str",{".class":"NoneType"}]},"type_guard":null,"type_is":null,"unpack_kwargs":false,"variables":[]}},"is_overload":false,"var":{".class":"Var","flags":["is_ready","is_inferred"],"fullname":"mashumaro.core.meta.types.pack.pack_fraction","name":"pack_fraction","type":{".class":"CallableType","arg_kinds":[0],"arg_names":[null],"arg_types":["mashumaro.core.meta.types.common.ValueSpec"],"bound_args":[],"def_extras":{},"fallback":"builtins.function","from_concatenate":false,"implicit":false,"imprecise_arg_kinds":false,"is_ellipsis_args":false,"name":"pack_fraction","ret_type":{".class":"UnionType","items":["builtins.str",{".class":"NoneType"}]},"type_guard":null,"type_is":null,"unpack_kwargs":false,"variables":[]}}}},"pack_generic_serializable_type":{".class":"SymbolTableNode","kind":"Gdef","module_public":false,"node":{".class":"Decorator","func":{".class":"FuncDef","abstract_status":0,"arg_kinds":[0],"arg_names":["spec"],"dataclass_transform_spec":null,"flags":["is_decorated"],"fullname":"mashumaro.core.meta.types.pack.pack_generic_serializable_type","name":"pack_generic_serializable_type","type":{".class":"CallableType","arg_kinds":[0],"arg_names":["spec"],"arg_types":["mashumaro.core.meta.types.common.ValueSpec"],"bound_args":[],"def_extras":{"first_arg":null},"fallback":"builtins.function","from_concatenate":false,"implicit":false,"imprecise_arg_kinds":false,"is_ellipsis_args":false,"name":"pack_generic_serializable_type","ret_type":{".class":"UnionType","items":["builtins.str",{".class":"NoneType"}]},"type_guard":null,"type_is":null,"unpack_kwargs":false,"variables":[]}},"is_overload":false,"var":{".class":"Var","flags":["is_ready","is_inferred"],"fullname":"mashumaro.core.meta.types.pack.pack_generic_serializable_type","name":"pack_generic_serializable_type","type":{".class":"CallableType","arg_kinds":[0],"arg_names":[null],"arg_types":["mashumaro.core.meta.types.common.ValueSpec"],"bound_args":[],"def_extras":{},"fallback":"builtins.function","from_concatenate":false,"implicit":false,"imprecise_arg_kinds":false,"is_ellipsis_args":false,"name":"pack_generic_serializable_type","ret_type":{".class":"UnionType","items":["builtins.str",{".class":"NoneType"}]},"type_guard":null,"type_is":null,"unpack_kwargs":false,"variables":[]}}}},"pack_ipaddress":{".class":"SymbolTableNode","kind":"Gdef","module_public":false,"node":{".class":"Decorator","func":{".class":"FuncDef","abstract_status":0,"arg_kinds":[0],"arg_names":["spec"],"dataclass_transform_spec":null,"flags":["is_decorated"],"fullname":"mashumaro.core.meta.types.pack.pack_ipaddress","name":"pack_ipaddress","type":{".class":"CallableType","arg_kinds":[0],"arg_names":["spec"],"arg_types":["mashumaro.core.meta.types.common.ValueSpec"],"bound_args":[],"def_extras":{"first_arg":null},"fallback":"builtins.function","from_concatenate":false,"implicit":false,"imprecise_arg_kinds":false,"is_ellipsis_args":false,"name":"pack_ipaddress","ret_type":{".class":"UnionType","items":["builtins.str",{".class":"NoneType"}]},"type_guard":null,"type_is":null,"unpack_kwargs":false,"variables":[]}},"is_overload":false,"var":{".class":"Var","flags":["is_ready","is_inferred"],"fullname":"mashumaro.core.meta.types.pack.pack_ipaddress","name":"pack_ipaddress","type":{".class":"CallableType","arg_kinds":[0],"arg_names":[null],"arg_types":["mashumaro.core.meta.types.common.ValueSpec"],"bound_args":[],"def_extras":{},"fallback":"builtins.function","from_concatenate":false,"implicit":false,"imprecise_arg_kinds":false,"is_ellipsis_args":false,"name":"pack_ipaddress","ret_type":{".class":"UnionType","items":["builtins.str",{".class":"NoneType"}]},"type_guard":null,"type_is":null,"unpack_kwargs":false,"variables":[]}}}},"pack_literal":{".class":"SymbolTableNode","kind":"Gdef","module_public":false,"node":{".class":"FuncDef","abstract_status":0,"arg_kinds":[0],"arg_names":["spec"],"dataclass_transform_spec":null,"flags":[],"fullname":"mashumaro.core.meta.types.pack.pack_literal","name":"pack_literal","type":{".class":"CallableType","arg_kinds":[0],"arg_names":["spec"],"arg_types":["mashumaro.core.meta.types.common.ValueSpec"],"bound_args":[],"def_extras":{"first_arg":null},"fallback":"builtins.function","from_concatenate":false,"implicit":false,"imprecise_arg_kinds":false,"is_ellipsis_args":false,"name":"pack_literal","ret_type":"builtins.str","type_guard":null,"type_is":null,"unpack_kwargs":false,"variables":[]}}},"pack_named_tuple":{".class":"SymbolTableNode","kind":"Gdef","module_public":false,"node":{".class":"FuncDef","abstract_status":0,"arg_kinds":[0],"arg_names":["spec"],"dataclass_transform_spec":null,"flags":[],"fullname":"mashumaro.core.meta.types.pack.pack_named_tuple","name":"pack_named_tuple","type":{".class":"CallableType","arg_kinds":[0],"arg_names":["spec"],"arg_types":["mashumaro.core.meta.types.common.ValueSpec"],"bound_args":[],"def_extras":{"first_arg":null},"fallback":"builtins.function","from_concatenate":false,"implicit":false,"imprecise_arg_kinds":false,"is_ellipsis_args":false,"name":"pack_named_tuple","ret_type":"builtins.str","type_guard":null,"type_is":null,"unpack_kwargs":false,"variables":[]}}},"pack_number":{".class":"SymbolTableNode","kind":"Gdef","module_public":false,"node":{".class":"Decorator","func":{".class":"FuncDef","abstract_status":0,"arg_kinds":[0],"arg_names":["spec"],"dataclass_transform_spec":null,"flags":["is_decorated"],"fullname":"mashumaro.core.meta.types.pack.pack_number","name":"pack_number","type":{".class":"CallableType","arg_kinds":[0],"arg_names":["spec"],"arg_types":["mashumaro.core.meta.types.common.ValueSpec"],"bound_args":[],"def_extras":{"first_arg":null},"fallback":"builtins.function","from_concatenate":false,"implicit":false,"imprecise_arg_kinds":false,"is_ellipsis_args":false,"name":"pack_number","ret_type":{".class":"UnionType","items":["builtins.str",{".class":"NoneType"}]},"type_guard":null,"type_is":null,"unpack_kwargs":false,"variables":[]}},"is_overload":false,"var":{".class":"Var","flags":["is_ready","is_inferred"],"fullname":"mashumaro.core.meta.types.pack.pack_number","name":"pack_number","type":{".class":"CallableType","arg_kinds":[0],"arg_names":[null],"arg_types":["mashumaro.core.meta.types.common.ValueSpec"],"bound_args":[],"def_extras":{},"fallback":"builtins.function","from_concatenate":false,"implicit":false,"imprecise_arg_kinds":false,"is_ellipsis_args":false,"name":"pack_number","ret_type":{".class":"UnionType","items":["builtins.str",{".class":"NoneType"}]},"type_guard":null,"type_is":null,"unpack_kwargs":false,"variables":[]}}}},"pack_pathlike":{".class":"SymbolTableNode","kind":"Gdef","module_public":false,"node":{".class":"Decorator","func":{".class":"FuncDef","abstract_status":0,"arg_kinds":[0],"arg_names":["spec"],"dataclass_transform_spec":null,"flags":["is_decorated"],"fullname":"mashumaro.core.meta.types.pack.pack_pathlike","name":"pack_pathlike","type":{".class":"CallableType","arg_kinds":[0],"arg_names":["spec"],"arg_types":["mashumaro.core.meta.types.common.ValueSpec"],"bound_args":[],"def_extras":{"first_arg":null},"fallback":"builtins.function","from_concatenate":false,"implicit":false,"imprecise_arg_kinds":false,"is_ellipsis_args":false,"name":"pack_pathlike","ret_type":{".class":"UnionType","items":["builtins.str",{".class":"NoneType"}]},"type_guard":null,"type_is":null,"unpack_kwargs":false,"variables":[]}},"is_overload":false,"var":{".class":"Var","flags":["is_ready","is_inferred"],"fullname":"mashumaro.core.meta.types.pack.pack_pathlike","name":"pack_pathlike","type":{".class":"CallableType","arg_kinds":[0],"arg_names":[null],"arg_types":["mashumaro.core.meta.types.common.ValueSpec"],"bound_args":[],"def_extras":{},"fallback":"builtins.function","from_concatenate":false,"implicit":false,"imprecise_arg_kinds":false,"is_ellipsis_args":false,"name":"pack_pathlike","ret_type":{".class":"UnionType","items":["builtins.str",{".class":"NoneType"}]},"type_guard":null,"type_is":null,"unpack_kwargs":false,"variables":[]}}}},"pack_serializable_type":{".class":"SymbolTableNode","kind":"Gdef","module_public":false,"node":{".class":"Decorator","func":{".class":"FuncDef","abstract_status":0,"arg_kinds":[0],"arg_names":["spec"],"dataclass_transform_spec":null,"flags":["is_decorated"],"fullname":"mashumaro.core.meta.types.pack.pack_serializable_type","name":"pack_serializable_type","type":{".class":"CallableType","arg_kinds":[0],"arg_names":["spec"],"arg_types":["mashumaro.core.meta.types.common.ValueSpec"],"bound_args":[],"def_extras":{"first_arg":null},"fallback":"builtins.function","from_concatenate":false,"implicit":false,"imprecise_arg_kinds":false,"is_ellipsis_args":false,"name":"pack_serializable_type","ret_type":{".class":"UnionType","items":["builtins.str",{".class":"NoneType"}]},"type_guard":null,"type_is":null,"unpack_kwargs":false,"variables":[]}},"is_overload":false,"var":{".class":"Var","flags":["is_ready","is_inferred"],"fullname":"mashumaro.core.meta.types.pack.pack_serializable_type","name":"pack_serializable_type","type":{".class":"CallableType","arg_kinds":[0],"arg_names":[null],"arg_types":["mashumaro.core.meta.types.common.ValueSpec"],"bound_args":[],"def_extras":{},"fallback":"builtins.function","from_concatenate":false,"implicit":false,"imprecise_arg_kinds":false,"is_ellipsis_args":false,"name":"pack_serializable_type","ret_type":{".class":"UnionType","items":["builtins.str",{".class":"NoneType"}]},"type_guard":null,"type_is":null,"unpack_kwargs":false,"variables":[]}}}},"pack_special_typing_primitive":{".class":"SymbolTableNode","kind":"Gdef","module_public":false,"node":{".class":"Decorator","func":{".class":"FuncDef","abstract_status":0,"arg_kinds":[0],"arg_names":["spec"],"dataclass_transform_spec":null,"flags":["is_decorated"],"fullname":"mashumaro.core.meta.types.pack.pack_special_typing_primitive","name":"pack_special_typing_primitive","type":{".class":"CallableType","arg_kinds":[0],"arg_names":["spec"],"arg_types":["mashumaro.core.meta.types.common.ValueSpec"],"bound_args":[],"def_extras":{"first_arg":null},"fallback":"builtins.function","from_concatenate":false,"implicit":false,"imprecise_arg_kinds":false,"is_ellipsis_args":false,"name":"pack_special_typing_primitive","ret_type":{".class":"UnionType","items":["builtins.str",{".class":"NoneType"}]},"type_guard":null,"type_is":null,"unpack_kwargs":false,"variables":[]}},"is_overload":false,"var":{".class":"Var","flags":["is_ready","is_inferred"],"fullname":"mashumaro.core.meta.types.pack.pack_special_typing_primitive","name":"pack_special_typing_primitive","type":{".class":"CallableType","arg_kinds":[0],"arg_names":[null],"arg_types":["mashumaro.core.meta.types.common.ValueSpec"],"bound_args":[],"def_extras":{},"fallback":"builtins.function","from_concatenate":false,"implicit":false,"imprecise_arg_kinds":false,"is_ellipsis_args":false,"name":"pack_special_typing_primitive","ret_type":{".class":"UnionType","items":["builtins.str",{".class":"NoneType"}]},"type_guard":null,"type_is":null,"unpack_kwargs":false,"variables":[]}}}},"pack_timedelta":{".class":"SymbolTableNode","kind":"Gdef","module_public":false,"node":{".class":"Decorator","func":{".class":"FuncDef","abstract_status":0,"arg_kinds":[0],"arg_names":["spec"],"dataclass_transform_spec":null,"flags":["is_decorated"],"fullname":"mashumaro.core.meta.types.pack.pack_timedelta","name":"pack_timedelta","type":{".class":"CallableType","arg_kinds":[0],"arg_names":["spec"],"arg_types":["mashumaro.core.meta.types.common.ValueSpec"],"bound_args":[],"def_extras":{"first_arg":null},"fallback":"builtins.function","from_concatenate":false,"implicit":false,"imprecise_arg_kinds":false,"is_ellipsis_args":false,"name":"pack_timedelta","ret_type":{".class":"UnionType","items":["builtins.str",{".class":"NoneType"}]},"type_guard":null,"type_is":null,"unpack_kwargs":false,"variables":[]}},"is_overload":false,"var":{".class":"Var","flags":["is_ready","is_inferred"],"fullname":"mashumaro.core.meta.types.pack.pack_timedelta","name":"pack_timedelta","type":{".class":"CallableType","arg_kinds":[0],"arg_names":[null],"arg_types":["mashumaro.core.meta.types.common.ValueSpec"],"bound_args":[],"def_extras":{},"fallback":"builtins.function","from_concatenate":false,"implicit":false,"imprecise_arg_kinds":false,"is_ellipsis_args":false,"name":"pack_timedelta","ret_type":{".class":"UnionType","items":["builtins.str",{".class":"NoneType"}]},"type_guard":null,"type_is":null,"unpack_kwargs":false,"variables":[]}}}},"pack_timezone":{".class":"SymbolTableNode","kind":"Gdef","module_public":false,"node":{".class":"Decorator","func":{".class":"FuncDef","abstract_status":0,"arg_kinds":[0],"arg_names":["spec"],"dataclass_transform_spec":null,"flags":["is_decorated"],"fullname":"mashumaro.core.meta.types.pack.pack_timezone","name":"pack_timezone","type":{".class":"CallableType","arg_kinds":[0],"arg_names":["spec"],"arg_types":["mashumaro.core.meta.types.common.ValueSpec"],"bound_args":[],"def_extras":{"first_arg":null},"fallback":"builtins.function","from_concatenate":false,"implicit":false,"imprecise_arg_kinds":false,"is_ellipsis_args":false,"name":"pack_timezone","ret_type":{".class":"UnionType","items":["builtins.str",{".class":"NoneType"}]},"type_guard":null,"type_is":null,"unpack_kwargs":false,"variables":[]}},"is_overload":false,"var":{".class":"Var","flags":["is_ready","is_inferred"],"fullname":"mashumaro.core.meta.types.pack.pack_timezone","name":"pack_timezone","type":{".class":"CallableType","arg_kinds":[0],"arg_names":[null],"arg_types":["mashumaro.core.meta.types.common.ValueSpec"],"bound_args":[],"def_extras":{},"fallback":"builtins.function","from_concatenate":false,"implicit":false,"imprecise_arg_kinds":false,"is_ellipsis_args":false,"name":"pack_timezone","ret_type":{".class":"UnionType","items":["builtins.str",{".class":"NoneType"}]},"type_guard":null,"type_is":null,"unpack_kwargs":false,"variables":[]}}}},"pack_tuple":{".class":"SymbolTableNode","kind":"Gdef","module_public":false,"node":{".class":"FuncDef","abstract_status":0,"arg_kinds":[0,0],"arg_names":["spec","args"],"dataclass_transform_spec":null,"flags":[],"fullname":"mashumaro.core.meta.types.pack.pack_tuple","name":"pack_tuple","type":{".class":"CallableType","arg_kinds":[0,0],"arg_names":["spec","args"],"arg_types":["mashumaro.core.meta.types.common.ValueSpec",{".class":"Instance","args":[{".class":"TypeType","item":{".class":"AnyType","missing_import_name":null,"source_any":null,"type_of_any":4}}],"type_ref":"builtins.tuple"}],"bound_args":[],"def_extras":{"first_arg":null},"fallback":"builtins.function","from_concatenate":false,"implicit":false,"imprecise_arg_kinds":false,"is_ellipsis_args":false,"name":"pack_tuple","ret_type":"builtins.str","type_guard":null,"type_is":null,"unpack_kwargs":false,"variables":[]}}},"pack_type_with_overridden_serialization":{".class":"SymbolTableNode","kind":"Gdef","module_public":false,"node":{".class":"Decorator","func":{".class":"FuncDef","abstract_status":0,"arg_kinds":[0],"arg_names":["spec"],"dataclass_transform_spec":null,"flags":["is_decorated"],"fullname":"mashumaro.core.meta.types.pack.pack_type_with_overridden_serialization","name":"pack_type_with_overridden_serialization","type":{".class":"CallableType","arg_kinds":[0],"arg_names":["spec"],"arg_types":["mashumaro.core.meta.types.common.ValueSpec"],"bound_args":[],"def_extras":{"first_arg":null},"fallback":"builtins.function","from_concatenate":false,"implicit":false,"imprecise_arg_kinds":false,"is_ellipsis_args":false,"name":"pack_type_with_overridden_serialization","ret_type":{".class":"UnionType","items":["builtins.str",{".class":"NoneType"}]},"type_guard":null,"type_is":null,"unpack_kwargs":false,"variables":[]}},"is_overload":false,"var":{".class":"Var","flags":["is_ready","is_inferred"],"fullname":"mashumaro.core.meta.types.pack.pack_type_with_overridden_serialization","name":"pack_type_with_overridden_serialization","type":{".class":"CallableType","arg_kinds":[0],"arg_names":[null],"arg_types":["mashumaro.core.meta.types.common.ValueSpec"],"bound_args":[],"def_extras":{},"fallback":"builtins.function","from_concatenate":false,"implicit":false,"imprecise_arg_kinds":false,"is_ellipsis_args":false,"name":"pack_type_with_overridden_serialization","ret_type":{".class":"UnionType","items":["builtins.str",{".class":"NoneType"}]},"type_guard":null,"type_is":null,"unpack_kwargs":false,"variables":[]}}}},"pack_typed_dict":{".class":"SymbolTableNode","kind":"Gdef","module_public":false,"node":{".class":"FuncDef","abstract_status":0,"arg_kinds":[0],"arg_names":["spec"],"dataclass_transform_spec":null,"flags":[],"fullname":"mashumaro.core.meta.types.pack.pack_typed_dict","name":"pack_typed_dict","type":{".class":"CallableType","arg_kinds":[0],"arg_names":["spec"],"arg_types":["mashumaro.core.meta.types.common.ValueSpec"],"bound_args":[],"def_extras":{"first_arg":null},"fallback":"builtins.function","from_concatenate":false,"implicit":false,"imprecise_arg_kinds":false,"is_ellipsis_args":false,"name":"pack_typed_dict","ret_type":"builtins.str","type_guard":null,"type_is":null,"unpack_kwargs":false,"variables":[]}}},"pack_union":{".class":"SymbolTableNode","kind":"Gdef","module_public":false,"node":{".class":"FuncDef","abstract_status":0,"arg_kinds":[0,0,1],"arg_names":["spec","args","prefix"],"dataclass_transform_spec":null,"flags":[],"fullname":"mashumaro.core.meta.types.pack.pack_union","name":"pack_union","type":{".class":"CallableType","arg_kinds":[0,0,1],"arg_names":["spec","args","prefix"],"arg_types":["mashumaro.core.meta.types.common.ValueSpec",{".class":"Instance","args":[{".class":"TypeType","item":{".class":"AnyType","missing_import_name":null,"source_any":null,"type_of_any":4}}],"type_ref":"builtins.tuple"},"builtins.str"],"bound_args":[],"def_extras":{"first_arg":null},"fallback":"builtins.function","from_concatenate":false,"implicit":false,"imprecise_arg_kinds":false,"is_ellipsis_args":false,"name":"pack_union","ret_type":"builtins.str","type_guard":null,"type_is":null,"unpack_kwargs":false,"variables":[]}}},"pack_uuid":{".class":"SymbolTableNode","kind":"Gdef","module_public":false,"node":{".class":"Decorator","func":{".class":"FuncDef","abstract_status":0,"arg_kinds":[0],"arg_names":["spec"],"dataclass_transform_spec":null,"flags":["is_decorated"],"fullname":"mashumaro.core.meta.types.pack.pack_uuid","name":"pack_uuid","type":{".class":"CallableType","arg_kinds":[0],"arg_names":["spec"],"arg_types":["mashumaro.core.meta.types.common.ValueSpec"],"bound_args":[],"def_extras":{"first_arg":null},"fallback":"builtins.function","from_concatenate":false,"implicit":false,"imprecise_arg_kinds":false,"is_ellipsis_args":false,"name":"pack_uuid","ret_type":{".class":"UnionType","items":["builtins.str",{".class":"NoneType"}]},"type_guard":null,"type_is":null,"unpack_kwargs":false,"variables":[]}},"is_overload":false,"var":{".class":"Var","flags":["is_ready","is_inferred"],"fullname":"mashumaro.core.meta.types.pack.pack_uuid","name":"pack_uuid","type":{".class":"CallableType","arg_kinds":[0],"arg_names":[null],"arg_types":["mashumaro.core.meta.types.common.ValueSpec"],"bound_args":[],"def_extras":{},"fallback":"builtins.function","from_concatenate":false,"implicit":false,"imprecise_arg_kinds":false,"is_ellipsis_args":false,"name":"pack_uuid","ret_type":{".class":"UnionType","items":["builtins.str",{".class":"NoneType"}]},"type_guard":null,"type_is":null,"unpack_kwargs":false,"variables":[]}}}},"pack_zone_info":{".class":"SymbolTableNode","kind":"Gdef","module_public":false,"node":{".class":"Decorator","func":{".class":"FuncDef","abstract_status":0,"arg_kinds":[0],"arg_names":["spec"],"dataclass_transform_spec":null,"flags":["is_decorated"],"fullname":"mashumaro.core.meta.types.pack.pack_zone_info","name":"pack_zone_info","type":{".class":"CallableType","arg_kinds":[0],"arg_names":["spec"],"arg_types":["mashumaro.core.meta.types.common.ValueSpec"],"bound_args":[],"def_extras":{"first_arg":null},"fallback":"builtins.function","from_concatenate":false,"implicit":false,"imprecise_arg_kinds":false,"is_ellipsis_args":false,"name":"pack_zone_info","ret_type":{".class":"UnionType","items":["builtins.str",{".class":"NoneType"}]},"type_guard":null,"type_is":null,"unpack_kwargs":false,"variables":[]}},"is_overload":false,"var":{".class":"Var","flags":["is_ready","is_inferred"],"fullname":"mashumaro.core.meta.types.pack.pack_zone_info","name":"pack_zone_info","type":{".class":"CallableType","arg_kinds":[0],"arg_names":[null],"arg_types":["mashumaro.core.meta.types.common.ValueSpec"],"bound_args":[],"def_extras":{},"fallback":"builtins.function","from_concatenate":false,"implicit":false,"imprecise_arg_kinds":false,"is_ellipsis_args":false,"name":"pack_zone_info","ret_type":{".class":"UnionType","items":["builtins.str",{".class":"NoneType"}]},"type_guard":null,"type_is":null,"unpack_kwargs":false,"variables":[]}}}},"pass_through":{".class":"SymbolTableNode","cross_ref":"mashumaro.helper.pass_through","kind":"Gdef","module_public":false},"random_hex":{".class":"SymbolTableNode","cross_ref":"mashumaro.core.meta.types.common.random_hex","kind":"Gdef","module_public":false},"register":{".class":"SymbolTableNode","kind":"Gdef","module_public":false,"node":{".class":"Var","flags":["is_inferred","has_explicit_value"],"fullname":"mashumaro.core.meta.types.pack.register","name":"register","type":{".class":"CallableType","arg_kinds":[0],"arg_names":["function"],"arg_types":[{".class":"TypeAliasType","args":[],"type_ref":"mashumaro.core.meta.types.common.ValueSpecExprCreator"}],"bound_args":["mashumaro.core.meta.types.common.Registry"],"def_extras":{"first_arg":"self"},"fallback":"builtins.function","from_concatenate":false,"implicit":false,"imprecise_arg_kinds":false,"is_ellipsis_args":false,"name":null,"ret_type":{".class":"TypeAliasType","args":[],"type_ref":"mashumaro.core.meta.types.common.ValueSpecExprCreator"},"type_guard":null,"type_is":null,"unpack_kwargs":false,"variables":[]}}},"resolve_type_params":{".class":"SymbolTableNode","cross_ref":"mashumaro.core.meta.helpers.resolve_type_params","kind":"Gdef","module_public":false},"substitute_type_params":{".class":"SymbolTableNode","cross_ref":"mashumaro.core.meta.helpers.substitute_type_params","kind":"Gdef","module_public":false},"suppress":{".class":"SymbolTableNode","cross_ref":"contextlib.suppress","kind":"Gdef","module_public":false},"type_name":{".class":"SymbolTableNode","cross_ref":"mashumaro.core.meta.helpers.type_name","kind":"Gdef","module_public":false},"typing":{".class":"SymbolTableNode","cross_ref":"typing","kind":"Gdef","module_public":false},"typing_extensions":{".class":"SymbolTableNode","cross_ref":"typing_extensions","kind":"Gdef","module_public":false},"uuid":{".class":"SymbolTableNode","cross_ref":"uuid","kind":"Gdef","module_public":false},"zoneinfo":{".class":"SymbolTableNode","cross_ref":"zoneinfo","kind":"Gdef","module_public":false}},"path":"c:\\Users\\ethan\\coding_projects\\pypreql-etl\\.venv\\Lib\\site-packages\\mashumaro\\core\\meta\\types\\pack.py"}